llama_index/readers/boarddocs/__init__.py
llama_index/readers/boarddocs/base.py
llama_index_readers_boarddocs-0.4.1.dist-info/METADATA
llama_index_readers_boarddocs-0.4.1.dist-info/WHEEL
llama_index_readers_boarddocs-0.4.1.dist-info/licenses/LICENSE
llama_index_readers_boarddocs-0.4.1.dist-info/RECORD
