Metadata-Version: 2.4
Name: llama-index-readers-boarddocs
Version: 0.4.1
Summary: llama-index readers boarddocs integration
Author-email: Your Name <you@example.com>
Maintainer: dweekly
License-Expression: GPL-3.0-or-later
License-File: LICENSE
Keywords: board,boarddocs
Requires-Python: <4.0,>=3.9
Requires-Dist: beautifulsoup4<5.0.0,>=4.12.3
Requires-Dist: html2text<2021,>=2020.1.16
Requires-Dist: llama-index-core<0.15,>=0.13.0
Requires-Dist: requests<3,>=2.31.0
